obf/__init__.py
obf/codewords.txt
obf/commandline.py
obf/obf.py
obf-1.0.0.dist-info/LICENSE.txt
obf-1.0.0.dist-info/METADATA
obf-1.0.0.dist-info/WHEEL
obf-1.0.0.dist-info/entry_points.txt
obf-1.0.0.dist-info/top_level.txt
obf-1.0.0.dist-info/RECORD
