Metadata-Version: 2.1
Name: obf
Version: 1.0.0
Summary: an obfuscation tool and library
Home-page: https://github.com/hossg/obf
Author: Hossein Ghodse
Author-email: hossein.ghodse@gmail.com
License: UNKNOWN
Platform: UNKNOWN
Classifier: Programming Language :: Python :: 3
Classifier: License :: OSI Approved :: GNU Affero General Public License v3
Classifier: Operating System :: OS Independent
